Workbook
Name Slicer_Channel1: #N/A
Name Slicer_Country: #N/A
Name Slicer_Payment_Type: #N/A
Name Slicer_Year: #N/A

Sheet REPORT
A3: Weekend/Weekdays | B3: Sales | C3: Profit | E3: Weekend/Weekdays | F3: Sales | G3: Profit | I3: Sum of Sales | J3: Weekend/Weekdays | M3: Sum of Profit | N3: Weekend/Weekdays | Q3: Weekend/Weekdays | R3: Profit | T3: Sales | U3: Total Orders | V3: Profit | W3: Total Customers | X3: Cost of Goods | Y3: Average Sales | AA3: Payment Type | AB3: Sum of Sales | AD3: Category | AE3: Sum of Sales | AF3: Sum of Profit | AH3: Sum of Sales | AI3: Year | AO3: City | AP3: Sum of Sales
A4: Weekend | B4: 201020.4 | C4: 88058.461 | E4: Weekday | F4: 419189.23 | G4: 182215.88 | I4: City | J4: Weekend | K4: Grand Total | M4: City | N4: Weekend | O4: Grand Total | Q4: Weekday | R4: 182215.88 | T4: 288813.36 | U4: 2543 | V4: 126735.74 | W4: 928 | X4: 162077.62 | Y4: 311.22129 | AA4: Cash | AB4: 16090.54 | AD4: Accessories | AE4: 94.44 | AF4: 45.894565 | AH4: Month | AI4: 2018 | AJ4: 2019 | AK4: 2020 | AL4: 2021 | AM4: Grand Total | AO4: Los Angeles | AP4: 17656.91
A5: Grand Total | B5: 201020.4 | C5: 88058.461 | E5: Grand Total | F5: 419189.23 | G5: 182215.88 | I5: Bend | J5: 133.37 | K5: 133.37 | M5: Bend | N5: 48.78 | O5: 48.78 | Q5: Weekend | R5: 88058.461 | AA5: Credit Card | AB5: 364239.27 | AD5: Apparel | AE5: 153216.93 | AF5: 65751.582 | AH5: January | AI5: 48115.59 | AJ5: 89483.74 | AK5: 139747.88 | AL5: 6314.14 | AM5: 283661.35 | AO5: Ottawa | AP5: 16230.19
I6: East Brunswick | J6: 133.37 | K6: 133.37 | M6: East Brunswick | N6: 48.78 | O6: 48.78 | Q6: Grand Total | R6: 270274.34 | AA6: Debit Card | AB6: 239879.82 | AD6: Biking | AE6: 4751.88 | AF6: 1944.86 | AH6: February | AI6: 13446.73 | AJ6: 6147.35 | AK6: 15548.38 | AM6: 35142.46 | AO6: Richmond | AP6: 19601.59
I7: El Paso | J7: 133.37 | K7: 133.37 | M7: El Paso | N7: 48.78 | O7: 48.78 | AA7: Grand Total | AB7: 620209.63 | AD7: Electronics | AE7: 150912.69 | AF7: 53310.151 | AH7: March | AI7: 3549.55 | AJ7: 5558.44 | AK7: 9000.63 | AM7: 18108.62 | AO7: Toronto | AP7: 13147.39
I8: Freeport | J8: 82.62 | K8: 82.62 | M8: Freeport | N8: 45.030001 | O8: 45.030001 | AD8: Fitness | AE8: 4433.28 | AF8: 2030.1552 | AH8: April | AI8: 17464.12 | AJ8: 5776.07 | AK8: 4917.97 | AM8: 28158.16 | AO8: Vancouver | AP8: 181891.71
I9: Glen Burnie | J9: 133.37 | K9: 133.37 | M9: Glen Burnie | N9: 48.78 | O9: 48.78 | AD9: Golf | AE9: 102773.69 | AF9: 28819.058 | AH9: May | AI9: 11507.02 | AJ9: 5614.45 | AK9: 5606.56 | AM9: 22728.03 | AO9: Grand Total | AP9: 248527.79
I10: Hampton | J10: 133.37 | K10: 133.37 | M10: Hampton | N10: 48.78 | O10: 48.78 | AD10: Outdoors | AE10: 23864.58 | AF10: 10267.94 | AH10: June | AI10: 12211.81 | AJ10: 8725.79 | AK10: 5696.49 | AM10: 26634.09
I11: Harvey | J11: 130 | K11: 130 | M11: Lithonia | N11: 48.78 | O11: 48.78 | AD11: Soccer | AE11: 180162.14 | AF11: 108104.7 | AH11: July | AI11: 8458.92 | AJ11: 7743.85 | AK11: 11966.91 | AM11: 28169.68
I12: Hyattsville | J12: 130 | K12: 130 | M12: Lutz | N12: 48.78 | O12: 48.78 | AD12: Grand Total | AE12: 620209.63 | AF12: 270274.34 | AH12: August | AI12: 11496.78 | AJ12: 15206.19 | AK12: 10772.6 | AM12: 37475.57
I13: Jackson | J13: 130 | K13: 130 | M13: Marysville | N13: 48.78 | O13: 48.78 | AH13: September | AI13: 6209.36 | AJ13: 5909.71 | AK13: 12703.11 | AM13: 24822.18
I14: Lithonia | J14: 133.37 | K14: 133.37 | M14: Plymouth | N14: 48.78 | O14: 48.78 | AH14: October | AI14: 17186.71 | AJ14: 14213.31 | AK14: 1737.61 | AM14: 33137.63
I15: Lutz | J15: 133.37 | K15: 133.37 | M15: Pomona | N15: 13.950003 | O15: 13.950003 | AH15: November | AI15: 5967.97 | AJ15: 10772.13 | AK15: 10305.96 | AM15: 27046.06
I16: Marion | J16: 94.75 | K16: 94.75 | M16: Quincy | N16: 48.78 | O16: 48.78 | AH16: December | AI16: 14199.22 | AJ16: 15118.15 | AK16: 25808.43 | AM16: 55125.8
I17: Marysville | J17: 133.37 | K17: 133.37 | M17: Squamish | N17: 48.78 | O17: 48.78 | AH17: Grand Total | AI17: 169813.78 | AJ17: 190269.18 | AK17: 253812.53 | AL17: 6314.14 | AM17: 620209.63
I18: Murfreesboro | J18: 130 | K18: 130 | M18: Union | N18: 48.78 | O18: 48.78
I19: Plymouth | J19: 133.37 | K19: 133.37 | M19: Grand Total | N19: 644.34 | O19: 644.34
I20: Pomona | J20: 27.97 | K20: 27.97
I21: Quincy | J21: 133.37 | K21: 133.37
I22: Squamish | J22: 133.37 | K22: 133.37
I23: Union | J23: 133.37 | K23: 133.37
I24: Van Nuys | J24: 130 | K24: 130
I25: Grand Total | J25: 2455.78 | K25: 2455.78

Sheet Dataset
A1: Order Id | B1: Order Date | C1: Day of the Week | D1: Weekend/Weekdays | E1: Month | F1: Year | G1: Customer Id | H1: Customer Last Name | I1: City | J1: Country | K1: Channel | L1: Payment Type | M1: Product | N1: Product ID | O1: Category | P1: Price | Q1: Quantity | R1: Sales | S1: COGS | T1: Profit | U1: Unit Cost
A2: 24118 | B2: 44196 | C2: =WEEKDAY(B2,2) -> 4 | D2: =IF(C2>=6,"Weekend","Weekday") -> Weekday | E2: =TEXT(Table2[[#This Row],[Order Date]],"MMMM") -> December | F2: =TEXT(Table2[[#This Row],[Order Date]],"YYYY") -> 2020 | G2: 9345 | H2: Branch | I2: Aurora | J2: USA | K2: Online | L2: Credit Card | M2: Glove It Women's Mod Oval Golf Glove | N2: 810 | O2: Golf | P2: 18.99 | Q2: 2 | R2: =P2*Q2 -> 37.98 | S2: 21.02 | T2: =R2-S2 -> 16.96 | U2: =S2/Q2 -> 10.51
A3: 24992 | B3: 44196 | C3: =WEEKDAY(B3,2) -> 4 | D3: =IF(C3>=6,"Weekend","Weekday") -> Weekday | E3: =TEXT(Table2[[#This Row],[Order Date]],"MMMM") -> December | F3: =TEXT(Table2[[#This Row],[Order Date]],"YYYY") -> 2020 | G3: 1169 | H3: Smith | I3: Denver | J3: USA | K3: Online | L3: Credit Card | M3: Mercurial Vapor 12 Academy Cleats | N3: 403 | O3: Soccer | P3: 133.37 | Q3: 1 | R3: =P3*Q3 -> 133.37 | S3: 84.59 | T3: =R3-S3 -> 48.78 | U3: =S3/Q3 -> 84.59
A4: 75928 | B4: 44196 | C4: =WEEKDAY(B4,2) -> 4 | D4: =IF(C4>=6,"Weekend","Weekday") -> Weekday | E4: =TEXT(Table2[[#This Row],[Order Date]],"MMMM") -> December | F4: =TEXT(Table2[[#This Row],[Order Date]],"YYYY") -> 2020 | G4: 19481 | H4: Jensen | I4: Seattle | J4: USA | K4: Online | L4: Credit Card | M4: Smart watch | N4: 1360 | O4: Electronics | P4: 370 | Q4: 1 | R4: =P4*Q4 -> 370 | S4: 249.09 | T4: =R4-S4 -> 120.91 | U4: =S4/Q4 -> 249.09
A5: 20755 | B5: 44195 | C5: =WEEKDAY(B5,2) -> 3 | D5: =IF(C5>=6,"Weekend","Weekday") -> Weekday | E5: =TEXT(Table2[[#This Row],[Order Date]],"MMMM") -> December | F5: =TEXT(Table2[[#This Row],[Order Date]],"YYYY") -> 2020 | G5: 640 | H5: Smith | I5: New Castle | J5: USA | K5: Online | L5: Credit Card | M5: Glove It Women's Imperial Golf Glove | N5: 804 | O5: Golf | P5: 18.99 | Q5: 2 | R5: =P5*Q5 -> 37.98 | S5: 23.639999 | T5: =R5-S5 -> 14.340001 | U5: =S5/Q5 -> 11.82
A6: 75741 | B6: 44194 | C6: =WEEKDAY(B6,2) -> 2 | D6: =IF(C6>=6,"Weekend","Weekday") -> Weekday | E6: =TEXT(Table2[[#This Row],[Order Date]],"MMMM") -> December | F6: =TEXT(Table2[[#This Row],[Order Date]],"YYYY") -> 2020 | G6: 19294 | H6: Patterson | I6: Chicago | J6: USA | K6: Online | L6: Credit Card | M6: Smart watch | N6: 1360 | O6: Electronics | P6: 370 | Q6: 1 | R6: =P6*Q6 -> 370 | S6: 249.09 | T6: =R6-S6 -> 120.91 | U6: =S6/Q6 -> 249.09
A7: 75742 | B7: 44193 | C7: =WEEKDAY(B7,2) -> 1 | D7: =IF(C7>=6,"Weekend","Weekday") -> Weekday | E7: =TEXT(Table2[[#This Row],[Order Date]],"MMMM") -> December | F7: =TEXT(Table2[[#This Row],[Order Date]],"YYYY") -> 2020 | G7: 19295 | H7: Nichols | I7: Anaheim | J7: USA | K7: Online | L7: Credit Card | M7: Smart watch | N7: 1360 | O7: Electronics | P7: 370 | Q7: 1 | R7: =P7*Q7 -> 370 | S7: 249.09 | T7: =R7-S7 -> 120.91 | U7: =S7/Q7 -> 249.09
A8: 75743 | B8: 44192 | C8: =WEEKDAY(B8,2) -> 7 | D8: =IF(C8>=6,"Weekend","Weekday") -> Weekend | E8: =TEXT(Table2[[#This Row],[Order Date]],"MMMM") -> December | F8: =TEXT(Table2[[#This Row],[Order Date]],"YYYY") -> 2020 | G8: 19296 | H8: Potter | I8: Miami | J8: USA | K8: Online | L8: Credit Card | M8: Smart watch | N8: 1360 | O8: Electronics | P8: 370 | Q8: 1 | R8: =P8*Q8 -> 370 | S8: 249.09 | T8: =R8-S8 -> 120.91 | U8: =S8/Q8 -> 249.09
A9: 75744 | B9: 44191 | C9: =WEEKDAY(B9,2) -> 6 | D9: =IF(C9>=6,"Weekend","Weekday") -> Weekend | E9: =TEXT(Table2[[#This Row],[Order Date]],"MMMM") -> December | F9: =TEXT(Table2[[#This Row],[Order Date]],"YYYY") -> 2020 | G9: 19297 | H9: Hopkins | I9: Loveland | J9: USA | K9: Online | L9: Credit Card | M9: Smart watch | N9: 1360 | O9: Electronics | P9: 370 | Q9: 1 | R9: =P9*Q9 -> 370 | S9: 249.09 | T9: =R9-S9 -> 120.91 | U9: =S9/Q9 -> 249.09
A10: 75745 | B10: 44190 | C10: =WEEKDAY(B10,2) -> 5 | D10: =IF(C10>=6,"Weekend","Weekday") -> Weekday | E10: =TEXT(Table2[[#This Row],[Order Date]],"MMMM") -> December | F10: =TEXT(Table2[[#This Row],[Order Date]],"YYYY") -> 2020 | G10: 19298 | H10: Middleton | I10: Coquitlam | J10: Canada | K10: In Store | L10: Cash | M10: Smart watch | N10: 1360 | O10: Electronics | P10: 370 | Q10: 1 | R10: =P10*Q10 -> 370 | S10: 249.09 | T10: =R10-S10 -> 120.91 | U10: =S10/Q10 -> 249.09
A11: 17582 | B11: 44190 | C11: =WEEKDAY(B11,2) -> 5 | D11: =IF(C11>=6,"Weekend","Weekday") -> Weekday | E11: =TEXT(Table2[[#This Row],[Order Date]],"MMMM") -> December | F11: =TEXT(Table2[[#This Row],[Order Date]],"YYYY") -> 2020 | G11: 5091 | H11: Smith | I11: Vancouver | J11: Canada | K11: In Store | L11: Credit Card | M11: Schwinn Comfort Bike Seat | N11: 957 | O11: Biking | P11: 80 | Q11: 1 | R11: =P11*Q11 -> 80 | S11: 47.43 | T11: =R11-S11 -> 32.57 | U11: =S11/Q11 -> 47.43
A12: 24548 | B12: 44190 | C12: =WEEKDAY(B12,2) -> 5 | D12: =IF(C12>=6,"Weekend","Weekday") -> Weekday | E12: =TEXT(Table2[[#This Row],[Order Date]],"MMMM") -> December | F12: =TEXT(Table2[[#This Row],[Order Date]],"YYYY") -> 2020 | G12: 6763 | H12: Salas | I12: Los Angeles | J12: USA | K12: Online | L12: Credit Card | M12: Mercurial Vapor 12 Academy Cleats | N12: 403 | O12: Soccer | P12: 133.37 | Q12: 1 | R12: =P12*Q12 -> 133.37 | S12: 84.59 | T12: =R12-S12 -> 48.78 | U12: =S12/Q12 -> 84.59
A13: 14960 | B13: 44189 | C13: =WEEKDAY(B13,2) -> 4 | D13: =IF(C13>=6,"Weekend","Weekday") -> Weekday | E13: =TEXT(Table2[[#This Row],[Order Date]],"MMMM") -> December | F13: =TEXT(Table2[[#This Row],[Order Date]],"YYYY") -> 2020 | G13: 9857 | H13: Deleon | I13: Vancouver | J13: Canada | K13: In Store | L13: Credit Card | M13: Sevylor Coleman 2-Person Outdoors Kayak | N13: 1004 | O13: Outdoors | P13: 460.58 | Q13: 1 | R13: =P13*Q13 -> 460.58 | S13: 268.79001 | T13: =R13-S13 -> 191.78999 | U13: =S13/Q13 -> 268.79001
... A2027: 91623 | B2027: 44206 | C2027: =WEEKDAY(B2027,2) -> 7 | D2027: =IF(C2027>=6,"Weekend","Weekday") -> Weekend | E2027: =TEXT(Table2[[#This Row],[Order Date]],"MMMM") -> January | F2027: =TEXT(Table2[[#This Row],[Order Date]],"YYYY") -> 2021 | G2027: 12059 | H2027: Dempsey | I2027: Coquitlam | J2027: Canada | K2027: Online | L2027: Credit Card | M2027: Mercurial Vapor 12 Academy Cleats | N2027: 403 | O2027: Soccer | P2027: 133.37 | Q2027: 1 | R2027: =P2027*Q2027 -> 133.37 | S2027: 84.59 | T2027: =R2027-S2027 -> 48.78 | U2027: =S2027/Q2027 -> 84.59

Sheet order details (USING VLOOKUP)
A1: order id | B1: order date | C1: customer id | D1: channel | E1: payment type | F1: product | G1: category | H1: sales price
A2: 16953 | B2: =VLOOKUP(A2,Sheet1!A:H,2,FALSE) -> 44184 | C2: =VLOOKUP(A2,Sheet1!A:H,3,FALSE) -> 2078 | D2: =VLOOKUP(A2,Sheet1!A:H,4,FALSE) -> In Store | E2: =VLOOKUP(A2,Sheet1!A:H,5,FALSE) -> Credit Card | F2: =VLOOKUP(A2,Sheet1!A:H,6,FALSE) -> Schwinn Comfort Bike Seat | G2: =VLOOKUP(A2,Sheet1!A:H,7,FALSE) -> Biking | H2: =VLOOKUP(A2,Sheet1!A:H,8,FALSE) -> 80
A3: 16864 | B3: =VLOOKUP(A3,Sheet1!A:H,2,FALSE) -> 44184 | C3: =VLOOKUP(A3,Sheet1!A:H,3,FALSE) -> 10992 | D3: =VLOOKUP(A3,Sheet1!A:H,4,FALSE) -> Online | E3: =VLOOKUP(A3,Sheet1!A:H,5,FALSE) -> Credit Card | F3: =VLOOKUP(A3,Sheet1!A:H,6,FALSE) -> Mercurial Vapor 13 Elite FG | G3: =VLOOKUP(A3,Sheet1!A:H,7,FALSE) -> Soccer | H3: =VLOOKUP(A3,Sheet1!A:H,8,FALSE) -> 94.75
A4: 10459 | B4: =VLOOKUP(A4,Sheet1!A:H,2,FALSE) -> 44184 | C4: =VLOOKUP(A4,Sheet1!A:H,3,FALSE) -> 9814 | D4: =VLOOKUP(A4,Sheet1!A:H,4,FALSE) -> Online | E4: =VLOOKUP(A4,Sheet1!A:H,5,FALSE) -> Debit Card | F4: =VLOOKUP(A4,Sheet1!A:H,6,FALSE) -> MAZEL Two Way Golf Putter | G4: =VLOOKUP(A4,Sheet1!A:H,7,FALSE) -> Golf | H4: =VLOOKUP(A4,Sheet1!A:H,8,FALSE) -> 211.96
A5: 18857 | B5: =VLOOKUP(A5,Sheet1!A:H,2,FALSE) -> 44183 | C5: =VLOOKUP(A5,Sheet1!A:H,3,FALSE) -> 4838 | D5: =VLOOKUP(A5,Sheet1!A:H,4,FALSE) -> In Store | E5: =VLOOKUP(A5,Sheet1!A:H,5,FALSE) -> Credit Card | F5: =VLOOKUP(A5,Sheet1!A:H,6,FALSE) -> Schwinn Comfort Bike Seat | G5: =VLOOKUP(A5,Sheet1!A:H,7,FALSE) -> Biking | H5: =VLOOKUP(A5,Sheet1!A:H,8,FALSE) -> 80
A6: 16081 | B6: =VLOOKUP(A6,Sheet1!A:H,2,FALSE) -> 44183 | C6: =VLOOKUP(A6,Sheet1!A:H,3,FALSE) -> 5367 | D6: =VLOOKUP(A6,Sheet1!A:H,4,FALSE) -> Online | E6: =VLOOKUP(A6,Sheet1!A:H,5,FALSE) -> Credit Card | F6: =VLOOKUP(A6,Sheet1!A:H,6,FALSE) -> Mercurial Vapor 12 Academy Cleats | G6: =VLOOKUP(A6,Sheet1!A:H,7,FALSE) -> Soccer | H6: =VLOOKUP(A6,Sheet1!A:H,8,FALSE) -> 133.37
A7: 49878 | B7: =VLOOKUP(A7,Sheet1!A:H,2,FALSE) -> 44183 | C7: =VLOOKUP(A7,Sheet1!A:H,3,FALSE) -> 1564 | D7: =VLOOKUP(A7,Sheet1!A:H,4,FALSE) -> Online | E7: =VLOOKUP(A7,Sheet1!A:H,5,FALSE) -> Debit Card | F7: =VLOOKUP(A7,Sheet1!A:H,6,FALSE) -> Taylormade Rocketballz Golf Balls | G7: =VLOOKUP(A7,Sheet1!A:H,7,FALSE) -> Golf | H7: =VLOOKUP(A7,Sheet1!A:H,8,FALSE) -> 186.76
A8: 48098 | B8: =VLOOKUP(A8,Sheet1!A:H,2,FALSE) -> 44180 | C8: =VLOOKUP(A8,Sheet1!A:H,3,FALSE) -> 4238 | D8: =VLOOKUP(A8,Sheet1!A:H,4,FALSE) -> Online | E8: =VLOOKUP(A8,Sheet1!A:H,5,FALSE) -> Credit Card | F8: =VLOOKUP(A8,Sheet1!A:H,6,FALSE) -> Mercurial Vapor 13 Elite FG | G8: =VLOOKUP(A8,Sheet1!A:H,7,FALSE) -> Soccer | H8: =VLOOKUP(A8,Sheet1!A:H,8,FALSE) -> 94.75
A9: 75774 | B9: =VLOOKUP(A9,Sheet1!A:H,2,FALSE) -> 44180 | C9: =VLOOKUP(A9,Sheet1!A:H,3,FALSE) -> 19327 | D9: =VLOOKUP(A9,Sheet1!A:H,4,FALSE) -> Online | E9: =VLOOKUP(A9,Sheet1!A:H,5,FALSE) -> Credit Card | F9: =VLOOKUP(A9,Sheet1!A:H,6,FALSE) -> Smart watch | G9: =VLOOKUP(A9,Sheet1!A:H,7,FALSE) -> Electronics | H9: =VLOOKUP(A9,Sheet1!A:H,8,FALSE) -> 370
A10: 15042 | B10: =VLOOKUP(A10,Sheet1!A:H,2,FALSE) -> 44180 | C10: =VLOOKUP(A10,Sheet1!A:H,3,FALSE) -> 1443 | D10: =VLOOKUP(A10,Sheet1!A:H,4,FALSE) -> Online | E10: =VLOOKUP(A10,Sheet1!A:H,5,FALSE) -> Debit Card | F10: =VLOOKUP(A10,Sheet1!A:H,6,FALSE) -> Air Zoom Pegasus 37 | G10: =VLOOKUP(A10,Sheet1!A:H,7,FALSE) -> Apparel | H10: =VLOOKUP(A10,Sheet1!A:H,8,FALSE) -> 340
A11: 21312 | B11: =VLOOKUP(A11,Sheet1!A:H,2,FALSE) -> 44179 | C11: =VLOOKUP(A11,Sheet1!A:H,3,FALSE) -> 6706 | D11: =VLOOKUP(A11,Sheet1!A:H,4,FALSE) -> In Store | E11: =VLOOKUP(A11,Sheet1!A:H,5,FALSE) -> Debit Card | F11: =VLOOKUP(A11,Sheet1!A:H,6,FALSE) -> Women's X-Tech Golf Glove Left Hand | G11: =VLOOKUP(A11,Sheet1!A:H,7,FALSE) -> Golf | H11: =VLOOKUP(A11,Sheet1!A:H,8,FALSE) -> 274.25
A12: 51298 | B12: =VLOOKUP(A12,Sheet1!A:H,2,FALSE) -> 44179 | C12: =VLOOKUP(A12,Sheet1!A:H,3,FALSE) -> 9272 | D12: =VLOOKUP(A12,Sheet1!A:H,4,FALSE) -> Online | E12: =VLOOKUP(A12,Sheet1!A:H,5,FALSE) -> Credit Card | F12: =VLOOKUP(A12,Sheet1!A:H,6,FALSE) -> Dri-FIT Victory Golf Polo | G12: =VLOOKUP(A12,Sheet1!A:H,7,FALSE) -> Apparel | H12: =VLOOKUP(A12,Sheet1!A:H,8,FALSE) -> 325
A13: 10595 | B13: =VLOOKUP(A13,Sheet1!A:H,2,FALSE) -> 44179 | C13: =VLOOKUP(A13,Sheet1!A:H,3,FALSE) -> 11034 | D13: =VLOOKUP(A13,Sheet1!A:H,4,FALSE) -> Online | E13: =VLOOKUP(A13,Sheet1!A:H,5,FALSE) -> Credit Card | F13: =VLOOKUP(A13,Sheet1!A:H,6,FALSE) -> Mercurial Vapor 12 Academy Cleats | G13: =VLOOKUP(A13,Sheet1!A:H,7,FALSE) -> Soccer | H13: =VLOOKUP(A13,Sheet1!A:H,8,FALSE) -> 133.37
... A85: 91623 | B85: =VLOOKUP(A85,Sheet1!A:H,2,FALSE) -> 44206 | C85: =VLOOKUP(A85,Sheet1!A:H,3,FALSE) -> 12059 | D85: =VLOOKUP(A85,Sheet1!A:H,4,FALSE) -> Online | E85: =VLOOKUP(A85,Sheet1!A:H,5,FALSE) -> Credit Card | F85: =VLOOKUP(A85,Sheet1!A:H,6,FALSE) -> Mercurial Vapor 12 Academy Cleats | G85: =VLOOKUP(A85,Sheet1!A:H,7,FALSE) -> Soccer | H85: =VLOOKUP(A85,Sheet1!A:H,8,FALSE) -> 133.37

Sheet Sheet1
A1: Order Id | B1: Order Date | C1: Customer Id | D1: Channel | E1: Payment Type | F1: Product | G1: Category | H1: Sales | M1: Price | N1: Quantity
A2: 24118 | B2: 44196 | C2: 9345 | D2: Online | E2: Credit Card | F2: Glove It Women's Mod Oval Golf Glove | G2: Golf | H2: =M2*N2 -> 37.98 | M2: 18.99 | N2: 2
A3: 24992 | B3: 44196 | C3: 1169 | D3: Online | E3: Credit Card | F3: Mercurial Vapor 12 Academy Cleats | G3: Soccer | H3: =M3*N3 -> 133.37 | M3: 133.37 | N3: 1
A4: 75928 | B4: 44196 | C4: 19481 | D4: Online | E4: Credit Card | F4: Smart watch | G4: Electronics | H4: =M4*N4 -> 370 | M4: 370 | N4: 1
A5: 20755 | B5: 44195 | C5: 640 | D5: Online | E5: Credit Card | F5: Glove It Women's Imperial Golf Glove | G5: Golf | H5: =M5*N5 -> 37.98 | M5: 18.99 | N5: 2
A6: 75741 | B6: 44194 | C6: 19294 | D6: Online | E6: Credit Card | F6: Smart watch | G6: Electronics | H6: =M6*N6 -> 370 | M6: 370 | N6: 1
A7: 75742 | B7: 44193 | C7: 19295 | D7: Online | E7: Credit Card | F7: Smart watch | G7: Electronics | H7: =M7*N7 -> 370 | M7: 370 | N7: 1
A8: 75743 | B8: 44192 | C8: 19296 | D8: Online | E8: Credit Card | F8: Smart watch | G8: Electronics | H8: =M8*N8 -> 370 | M8: 370 | N8: 1
A9: 75744 | B9: 44191 | C9: 19297 | D9: Online | E9: Credit Card | F9: Smart watch | G9: Electronics | H9: =M9*N9 -> 370 | M9: 370 | N9: 1
A10: 75745 | B10: 44190 | C10: 19298 | D10: In Store | E10: Cash | F10: Smart watch | G10: Electronics | H10: =M10*N10 -> 370 | M10: 370 | N10: 1
A11: 17582 | B11: 44190 | C11: 5091 | D11: In Store | E11: Credit Card | F11: Schwinn Comfort Bike Seat | G11: Biking | H11: =M11*N11 -> 80 | M11: 80 | N11: 1
A12: 24548 | B12: 44190 | C12: 6763 | D12: Online | E12: Credit Card | F12: Mercurial Vapor 12 Academy Cleats | G12: Soccer | H12: =M12*N12 -> 133.37 | M12: 133.37 | N12: 1
A13: 14960 | B13: 44189 | C13: 9857 | D13: In Store | E13: Credit Card | F13: Sevylor Coleman 2-Person Outdoors Kayak | G13: Outdoors | H13: =M13*N13 -> 460.58 | M13: 460.58 | N13: 1
... A2027: 91623 | B2027: 44206 | C2027: 12059 | D2027: Online | E2027: Credit Card | F2027: Mercurial Vapor 12 Academy Cleats | G2027: Soccer | H2027: =M2027*N2027 -> 133.37 | M2027: 133.37 | N2027: 1

Sheet Dashboard
S10: Insights: *Customers seem to prefer cashless payments.
T11: *Toronto and Ottawa has the lowest amount of sales therefore those areas need more marketing, while Vancouver has the highest sales amount so it is worth more investment.
T12: *Weekdays bring in more profit than weekends, so more weekend shopping should be encouraged and promoted.
T13: *Soccer, electronics, and apparel brings in high revenue, while other categories sell but they don't generate enough profit, which could be due to the product cost.
T14: *There is more in-store sales than online, so the physical store is very much needed.

Sheet Sheet2
